mx_rmq/__init__.py
mx_rmq/config.py
mx_rmq/constants.py
mx_rmq/log_config.py
mx_rmq/message.py
mx_rmq/queue.py
mx_rmq/signal_handler.py
mx_rmq/core/__init__.py
mx_rmq/core/consumer.py
mx_rmq/core/context.py
mx_rmq/core/dispatch.py
mx_rmq/core/lifecycle.py
mx_rmq/core/schedule.py
mx_rmq/monitoring/__init__.py
mx_rmq/monitoring/metrics.py
mx_rmq/resources/__init__.py
mx_rmq/resources/lua_scripts/__init__.py
mx_rmq/resources/lua_scripts/consumer/__init__.py
mx_rmq/resources/lua_scripts/consumer/get_next_delay_task.lua
mx_rmq/resources/lua_scripts/consumer/process_delay_message.lua
mx_rmq/resources/lua_scripts/lifecycle/__init__.py
mx_rmq/resources/lua_scripts/lifecycle/complete_message.lua
mx_rmq/resources/lua_scripts/lifecycle/retry_message.lua
mx_rmq/resources/lua_scripts/management/__init__.py
mx_rmq/resources/lua_scripts/management/handle_parse_error.lua
mx_rmq/resources/lua_scripts/management/handle_timeout_message.lua
mx_rmq/resources/lua_scripts/management/move_to_dlq.lua
mx_rmq/resources/lua_scripts/producer/__init__.py
mx_rmq/resources/lua_scripts/producer/produce_delay_message.lua
mx_rmq/resources/lua_scripts/producer/produce_normal_message.lua
mx_rmq/storage/__init__.py
mx_rmq/storage/connection_manager.py
mx_rmq/storage/lua_manager.py
mx_rmq-1.6.2.dist-info/METADATA
mx_rmq-1.6.2.dist-info/WHEEL
mx_rmq-1.6.2.dist-info/licenses/LICENSE
mx_rmq-1.6.2.dist-info/RECORD
