Metadata-Version: 2.4
Name: mx-rmq
Version: 1.6.2
Summary: 基于Redis的异步消息队列系统
Project-URL: Homepage, https://github.com/CodingOX/mx-rmq
Project-URL: Repository, https://github.com/CodingOX/mx-rmq
Project-URL: Documentation, https://github.com/CodingOX/mx-rmq#readme
Project-URL: Issues, https://github.com/CodingOX/mx-rmq/issues
Author-email: Alistar Max <codingox@gmail.com>
License: MIT
License-File: LICENSE
Keywords: async,distributed,message-queue,redis
Classifier: Development Status :: 5 - Production/Stable
Classifier: Intended Audience :: Developers
Classifier: License :: OSI Approved :: MIT License
Classifier: Programming Language :: Python :: 3
Classifier: Programming Language :: Python :: 3.10
Classifier: Topic :: Software Development :: Libraries :: Python Modules
Classifier: Topic :: System :: Distributed Computing
Requires-Python: >=3.10
Requires-Dist: loguru>=0.7.3
Requires-Dist: pydantic>=2.11.7
Requires-Dist: redis[hiredis]>=6.3.0
Provides-Extra: dev
Requires-Dist: black>=25.1.0; extra == 'dev'
Requires-Dist: mypy>=1.17.1; extra == 'dev'
Requires-Dist: pytest-asyncio>=1.1.0; extra == 'dev'
Requires-Dist: pytest-cov>=6.2.1; extra == 'dev'
Requires-Dist: pytest>=8.4.1; extra == 'dev'
Requires-Dist: ruff>=0.12.7; extra == 'dev'
